sphinxcontrib_trimblank-1.0.3-py3.9-nspkg.pth
sphinxcontrib/trimblank.py
sphinxcontrib_trimblank-1.0.3.dist-info/LICENSE
sphinxcontrib_trimblank-1.0.3.dist-info/METADATA
sphinxcontrib_trimblank-1.0.3.dist-info/WHEEL
sphinxcontrib_trimblank-1.0.3.dist-info/namespace_packages.txt
sphinxcontrib_trimblank-1.0.3.dist-info/top_level.txt
sphinxcontrib_trimblank-1.0.3.dist-info/RECORD
