Metadata-Version: 2.1
Name: sphinxcontrib-trimblank
Version: 1.0.3
Summary: A Sphinx extension which trims redundant blanks
Home-page: https://github.com/amedama41/sphinxcontrib-trimblank
Author: amedama41
Author-email: kamo.devel41@gmail.com
Keywords: sphinx,extension
Classifier: Framework :: Sphinx :: Extension
Classifier: License :: OSI Approved :: MIT License
Classifier: Programming Language :: Python :: 3
Classifier: Topic :: Documentation :: Sphinx
Requires-Python: >=3.5.*
License-File: LICENSE
Requires-Dist: Sphinx
